tigzig_api_monitor/__init__.py
tigzig_api_monitor/middleware.py
tigzig_api_monitor-1.3.1.dist-info/METADATA
tigzig_api_monitor-1.3.1.dist-info/WHEEL
tigzig_api_monitor-1.3.1.dist-info/RECORD
