Metadata-Version: 2.4
Name: tigzig-api-monitor
Version: 1.3.1
Summary: Lightweight FastAPI middleware for centralized API monitoring
Project-URL: Homepage, https://github.com/amararun/TIGZIG_LOGGER_SERVICE
Project-URL: Repository, https://github.com/amararun/TIGZIG_LOGGER_SERVICE
Project-URL: Issues, https://github.com/amararun/TIGZIG_LOGGER_SERVICE/issues
Author-email: Amar Harolikar <amar@harolikar.com>
License: MIT
Keywords: analytics,api,fastapi,logging,middleware,monitoring
Classifier: Development Status :: 4 - Beta
Classifier: Framework :: FastAPI
Classifier: Intended Audience :: Developers
Classifier: License :: OSI Approved :: MIT License
Classifier: Operating System :: OS Independent
Classifier: Programming Language :: Python :: 3
Classifier: Programming Language :: Python :: 3.8
Classifier: Programming Language :: Python :: 3.9
Classifier: Programming Language :: Python :: 3.10
Classifier: Programming Language :: Python :: 3.11
Classifier: Programming Language :: Python :: 3.12
Classifier: Topic :: Internet :: WWW/HTTP :: HTTP Servers
Classifier: Topic :: System :: Logging
Classifier: Topic :: System :: Monitoring
Requires-Python: >=3.8
Requires-Dist: httpx>=0.24.0
Requires-Dist: starlette>=0.27.0
